IPPy/__init__.py
IPPy/operators.py
IPPy/solvers.py
IPPy/nn/__init__.py
IPPy/nn/_blocks.py
IPPy/nn/_utilities.py
IPPy/nn/losses.py
IPPy/nn/models.py
IPPy/nn/trainer.py
IPPy/utilities/__init__.py
IPPy/utilities/_utilities.py
IPPy/utilities/data.py
IPPy/utilities/metrics.py
inverse_problems_Python-1.0.1.dist-info/LICENSE
inverse_problems_Python-1.0.1.dist-info/METADATA
inverse_problems_Python-1.0.1.dist-info/WHEEL
inverse_problems_Python-1.0.1.dist-info/top_level.txt
inverse_problems_Python-1.0.1.dist-info/RECORD
